python_fantales.py
setup.py
python_fantales.egg-info/PKG-INFO
python_fantales.egg-info/SOURCES.txt
python_fantales.egg-info/dependency_links.txt
python_fantales.egg-info/top_level.txt