Metadata-Version: 1.0
Name: python-fantales
Version: 0.1
Summary: helps to visualise opinions of movie fans derived from a survey
Home-page: UNKNOWN
Author: Sapna Jadon
Author-email: jadon.sapna11@gmail.com
License: BSD
Keywords: Html,fans,xml
Platform: any
